odoo/addons/l10n_es_aeat_mod349/README.rst
odoo/addons/l10n_es_aeat_mod349/__init__.py
odoo/addons/l10n_es_aeat_mod349/__manifest__.py
odoo/addons/l10n_es_aeat_mod349/hooks.py
odoo/addons/l10n_es_aeat_mod349/data/aeat_349_map_data.xml
odoo/addons/l10n_es_aeat_mod349/data/aeat_export_mod349_data.xml
odoo/addons/l10n_es_aeat_mod349/data/aeat_export_mod349_partner_data.xml
odoo/addons/l10n_es_aeat_mod349/data/aeat_export_mod349_partner_refund_data.xml
odoo/addons/l10n_es_aeat_mod349/docs/BOE-A-2010-5098.pdf
odoo/addons/l10n_es_aeat_mod349/docs/NREG-349-2016.docx
odoo/addons/l10n_es_aeat_mod349/i18n/es.po
odoo/addons/l10n_es_aeat_mod349/i18n/l10n_es_aeat_mod349.pot
odoo/addons/l10n_es_aeat_mod349/models/__init__.py
odoo/addons/l10n_es_aeat_mod349/models/account_invoice.py
odoo/addons/l10n_es_aeat_mod349/models/account_move_line.py
odoo/addons/l10n_es_aeat_mod349/models/account_tax.py
odoo/addons/l10n_es_aeat_mod349/models/account_tax_template.py
odoo/addons/l10n_es_aeat_mod349/models/aeat_349_map_line.py
odoo/addons/l10n_es_aeat_mod349/models/mod349.py
odoo/addons/l10n_es_aeat_mod349/readme/CONTRIBUTORS.rst
odoo/addons/l10n_es_aeat_mod349/readme/DESCRIPTION.rst
odoo/addons/l10n_es_aeat_mod349/readme/ROADMAP.rst
odoo/addons/l10n_es_aeat_mod349/readme/USAGE.rst
odoo/addons/l10n_es_aeat_mod349/report/aeat_mod349.xml
odoo/addons/l10n_es_aeat_mod349/report/common_templates.xml
odoo/addons/l10n_es_aeat_mod349/report/report_views.xml
odoo/addons/l10n_es_aeat_mod349/security/ir.model.access.csv
odoo/addons/l10n_es_aeat_mod349/security/mod_349_security.xml
odoo/addons/l10n_es_aeat_mod349/static/description/icon.png
odoo/addons/l10n_es_aeat_mod349/static/description/icon_source.svg
odoo/addons/l10n_es_aeat_mod349/static/description/index.html
odoo/addons/l10n_es_aeat_mod349/tests/__init__.py
odoo/addons/l10n_es_aeat_mod349/tests/test_l10n_es_aeat_mod349.py
odoo/addons/l10n_es_aeat_mod349/views/account_invoice_view.xml
odoo/addons/l10n_es_aeat_mod349/views/account_move_view.xml
odoo12_addon_l10n_es_aeat_mod349-12.0.1.3.4.dist-info/METADATA
odoo12_addon_l10n_es_aeat_mod349-12.0.1.3.4.dist-info/WHEEL
odoo12_addon_l10n_es_aeat_mod349-12.0.1.3.4.dist-info/top_level.txt
odoo12_addon_l10n_es_aeat_mod349-12.0.1.3.4.dist-info/RECORD
